crypto_factory/__init__.py
crypto_factory/exceptions.py
crypto_factory/factory.py
crypto_factory/interface.py
crypto_factory/providers.py
crypto_factory/templates.py
crypto_factory/utils.py
Crypto_Factory-0.0.9.dist-info/LICENSE
Crypto_Factory-0.0.9.dist-info/METADATA
Crypto_Factory-0.0.9.dist-info/WHEEL
Crypto_Factory-0.0.9.dist-info/top_level.txt
Crypto_Factory-0.0.9.dist-info/RECORD
