Metadata-Version: 2.1
Name: Crypto-Factory
Version: 0.0.9
Summary: Standardize cryptographic tasks in your application.
Home-page: https://github.com/LuckyDams/Crypto-Factory
Author: LuckyDams
Author-email: LuckyDams@gmail.org
License: MIT
Project-URL: Documentation, https://crypto-factory.readthedocs.io/en/latest/
Project-URL: Releases, https://pypi.org/project/Crypto-Factory
Project-URL: Source, https://github.com/LuckyDams/Crypto-Factory
Project-URL: Tracker, https://github.com/LuckyDams/Crypto-Factory/issues
Keywords: cryptography factory-design
Platform: any
Classifier: Development Status :: 4 - Beta
Classifier: License :: OSI Approved :: MIT License
Classifier: Operating System :: OS Independent
Classifier: Programming Language :: Python :: 3
Classifier: Programming Language :: Python :: 3.4
Classifier: Programming Language :: Python :: 3.5
Classifier: Programming Language :: Python :: 3.6
Classifier: Programming Language :: Python :: 3.7
Classifier: Topic :: Security :: Cryptography
Classifier: Topic :: Software Development :: Libraries :: Python Modules
Requires-Python: >=3.4
Requires-Dist: cryptography (>=2.3.0)
Requires-Dist: Attr-Dict (>=0.1.0)
